Naughty_and_Nice-7.7.1.dist-info/DESCRIPTION.rst
Naughty_and_Nice-7.7.1.dist-info/METADATA
Naughty_and_Nice-7.7.1.dist-info/RECORD
Naughty_and_Nice-7.7.1.dist-info/WHEEL
Naughty_and_Nice-7.7.1.dist-info/metadata.json
Naughty_and_Nice-7.7.1.dist-info/top_level.txt
naughty_and_nice/__init__.py
naughty_and_nice/naughtyandnice.py
