Metadata-Version: 2.0
Name: Naughty-and-Nice
Version: 7.7.1
Summary: A program that gets tweets off your API key in tweepy and analyizes a user's acount on twitter to see if they are naughty or nice.
Home-page: UNKNOWN
Author: xXTheProgrammerXx
Author-email: arhithprem@gmail.com
License: UNKNOWN
Keywords: twitter,learning
Platform: UNKNOWN
Classifier: Development Status :: 6 - Mature
Classifier: Intended Audience :: Education
Classifier: Programming Language :: Python :: 3
Requires: tweepy
Requires: json
Requires: re
Requires: string
Requires: nltk
